dictionarysnek/__init__.py
dictionarysnek/dictionarysnek.py
dictionarysnek-0.0.2.dist-info/WHEEL
dictionarysnek-0.0.2.dist-info/METADATA
dictionarysnek-0.0.2.dist-info/RECORD
